<solids><tube name="UTCH0x865" rmin="0" rmax="0.10000000149011612" z="108.09999847412109" startphi="0" deltaphi="360" aunit="deg" lunit="cm"/>
    <tube name="UTCP0x865" rmin="0" rmax="0.15000000596046448" z="108.09999847412109" startphi="0" deltaphi="360" aunit="deg" lunit="cm"/>
    <tube name="UTCH0x867" rmin="0" rmax="0.10000000149011612" z="108.09999847412109" startphi="0" deltaphi="360" aunit="deg" lunit="cm"/>
    <tube name="UTCP0x867" rmin="0" rmax="0.15000000596046448" z="108.09999847412109" startphi="0" deltaphi="360" aunit="deg" lunit="cm"/>
    <tube name="UTCH0x869" rmin="0" rmax="0.10000000149011612" z="108.09999847412109" startphi="0" deltaphi="360" aunit="deg" lunit="cm"/>
    <tube name="UTCP0x869" rmin="0" rmax="0.15000000596046448" z="108.09999847412109" startphi="0" deltaphi="360" aunit="deg" lunit="cm"/>
    <tube name="UTCH0x871" rmin="0" rmax="0.10000000149011612" z="108.09999847412109" startphi="0" deltaphi="360" aunit="deg" lunit="cm"/>
    <tube name="UTCP0x871" rmin="0" rmax="0.15000000596046448" z="108.09999847412109" startphi="0" deltaphi="360" aunit="deg" lunit="cm"/>
    <tube name="UTCH0x873" rmin="0" rmax="0.10000000149011612" z="108.09999847412109" startphi="0" deltaphi="360" aunit="deg" lunit="cm"/>
    <tube name="UTCP0x873" rmin="0" rmax="0.15000000596046448" z="108.09999847412109" startphi="0" deltaphi="360" aunit="deg" lunit="cm"/>
    <tube name="UTCH0x875" rmin="0" rmax="0.10000000149011612" z="108.09999847412109" startphi="0" deltaphi="360" aunit="deg" lunit="cm"/>
    <tube name="UTCP0x875" rmin="0" rmax="0.15000000596046448" z="108.09999847412109" startphi="0" deltaphi="360" aunit="deg" lunit="cm"/>
    <tube name="UTCH0x877" rmin="0" rmax="0.10000000149011612" z="108.09999847412109" startphi="0" deltaphi="360" aunit="deg" lunit="cm"/>
    <tube name="UTCP0x877" rmin="0" rmax="0.15000000596046448" z="108.09999847412109" startphi="0" deltaphi="360" aunit="deg" lunit="cm"/>
    <tube name="UTCH0x879" rmin="0" rmax="0.10000000149011612" z="108.09999847412109" startphi="0" deltaphi="360" aunit="deg" lunit="cm"/>
    <tube name="UTCP0x879" rmin="0" rmax="0.15000000596046448" z="108.09999847412109" startphi="0" deltaphi="360" aunit="deg" lunit="cm"/>
    <tube name="UTCH0x881" rmin="0" rmax="0.10000000149011612" z="108.09999847412109" startphi="0" deltaphi="360" aunit="deg" lunit="cm"/>
    <tube name="UTCP0x881" rmin="0" rmax="0.15000000596046448" z="108.09999847412109" startphi="0" deltaphi="360" aunit="deg" lunit="cm"/>
    <tube name="UTCH0x883" rmin="0" rmax="0.10000000149011612" z="108.09999847412109" startphi="0" deltaphi="360" aunit="deg" lunit="cm"/>
    <tube name="UTCP0x883" rmin="0" rmax="0.15000000596046448" z="108.09999847412109" startphi="0" deltaphi="360" aunit="deg" lunit="cm"/>
    <tube name="UTCH0x885" rmin="0" rmax="0.10000000149011612" z="108.09999847412109" startphi="0" deltaphi="360" aunit="deg" lunit="cm"/>
    <tube name="UTCP0x885" rmin="0" rmax="0.15000000596046448" z="108.09999847412109" startphi="0" deltaphi="360" aunit="deg" lunit="cm"/>
    <tube name="UTCH0x887" rmin="0" rmax="0.10000000149011612" z="108.09999847412109" startphi="0" deltaphi="360" aunit="deg" lunit="cm"/>
    <tube name="UTCP0x887" rmin="0" rmax="0.15000000596046448" z="108.09999847412109" startphi="0" deltaphi="360" aunit="deg" lunit="cm"/>
    <tube name="UTPL0x865" rmin="0" rmax="0.10000000149011612" z="108.09999847412109" startphi="0" deltaphi="360" aunit="deg" lunit="cm"/>
    <tube name="UTPL0x867" rmin="0" rmax="0.10000000149011612" z="108.09999847412109" startphi="0" deltaphi="360" aunit="deg" lunit="cm"/>
    <tube name="UTPL0x869" rmin="0" rmax="0.10000000149011612" z="108.09999847412109" startphi="0" deltaphi="360" aunit="deg" lunit="cm"/>
    <tube name="UTPL0x871" rmin="0" rmax="0.10000000149011612" z="108.09999847412109" startphi="0" deltaphi="360" aunit="deg" lunit="cm"/>
    <tube name="UTPL0x873" rmin="0" rmax="0.10000000149011612" z="108.09999847412109" startphi="0" deltaphi="360" aunit="deg" lunit="cm"/>
    <tube name="UTPL0x875" rmin="0" rmax="0.10000000149011612" z="108.09999847412109" startphi="0" deltaphi="360" aunit="deg" lunit="cm"/>
    <tube name="UTPL0x877" rmin="0" rmax="0.10000000149011612" z="108.09999847412109" startphi="0" deltaphi="360" aunit="deg" lunit="cm"/>
    <tube name="UTPL0x879" rmin="0" rmax="0.10000000149011612" z="108.09999847412109" startphi="0" deltaphi="360" aunit="deg" lunit="cm"/>
    <tube name="UTPL0x881" rmin="0" rmax="0.10000000149011612" z="108.09999847412109" startphi="0" deltaphi="360" aunit="deg" lunit="cm"/>
    <tube name="UTPL0x883" rmin="0" rmax="0.10000000149011612" z="108.09999847412109" startphi="0" deltaphi="360" aunit="deg" lunit="cm"/>
    <tube name="UTPL0x885" rmin="0" rmax="0.10000000149011612" z="108.09999847412109" startphi="0" deltaphi="360" aunit="deg" lunit="cm"/>
    <tube name="UTPL0x887" rmin="0" rmax="0.10000000149011612" z="108.09999847412109" startphi="0" deltaphi="360" aunit="deg" lunit="cm"/>
    <box name="UMC10x1" x="3" y="3" z="0.10000000149011612" lunit="cm"/>
    <box name="UMC20x1" x="3" y="3" z="0.0024999999441206455" lunit="cm"/>
    <box name="UMC30x1" x="3" y="3" z="0.029999999329447746" lunit="cm"/>
    <box name="UMC40x1" x="3" y="3" z="0.039999999105930328" lunit="cm"/>
    <box name="UMCM0x1" x="3" y="3" z="0.30000001192092896" lunit="cm"/>
    <box name="UU160x1" x="108.09999847412109" y="108" z="1.0420000553131104" lunit="cm"/>
    </solids>