<define><position name="SNPB_1inSCHLpos" x="0" y="0" z="-1.24695" unit="cm"/>
    <position name="SKPT_1inSCHLpos" x="0" y="0" z="0" unit="cm"/>
    <position name="SCHL_10x34inS235pos" x="-12.6" y="0" z="0" unit="cm"/>
    <position name="SCHL_20x21inS235pos" x="-7.5599999999999996" y="0" z="0" unit="cm"/>
    <position name="SCHL_30x18inS235pos" x="-2.5199999999999996" y="0" z="0" unit="cm"/>
    <position name="SCHL_40x12inS235pos" x="2.5199999999999996" y="0" z="0" unit="cm"/>
    <position name="SCHL_50x10inS235pos" x="7.5599999999999996" y="0" z="0" unit="cm"/>
    <position name="SCHL_60x9inS235pos" x="12.6" y="0" z="0" unit="cm"/>
    </define>