<define><position name="SNPB_1inSCHLpos" x="0" y="0" z="-1.24695" unit="cm"/>
    <position name="SKPT_1inSCHLpos" x="0" y="0" z="0" unit="cm"/>
    <position name="SCHL_10x8inS209pos" x="-20.159999999999997" y="0" z="0" unit="cm"/>
    <position name="SCHL_20x4inS209pos" x="-17.639999999999997" y="0" z="0" unit="cm"/>
    <position name="SCHL_30x4inS209pos" x="-15.119999999999999" y="0" z="0" unit="cm"/>
    <position name="SCHL_40x2inS209pos" x="-12.6" y="0" z="0" unit="cm"/>
    <position name="SCHL_50x2inS209pos" x="-10.079999999999998" y="0" z="0" unit="cm"/>
    <position name="SCHL_60x2inS209pos" x="-7.5599999999999996" y="0" z="0" unit="cm"/>
    <position name="SCHL_70x2inS209pos" x="-5.0399999999999991" y="0" z="0" unit="cm"/>
    <position name="SCHL_80x2inS209pos" x="-2.5199999999999996" y="0" z="0" unit="cm"/>
    <position name="SCHL_90x2inS209pos" x="0" y="0" z="0" unit="cm"/>
    <position name="SCHL_100x2inS209pos" x="2.5199999999999996" y="0" z="0" unit="cm"/>
    <position name="SCHL_110x2inS209pos" x="5.0399999999999991" y="0" z="0" unit="cm"/>
    <position name="SCHL_120x2inS209pos" x="7.5599999999999996" y="0" z="0" unit="cm"/>
    <position name="SCHL_130x2inS209pos" x="10.079999999999998" y="0" z="0" unit="cm"/>
    <position name="SCHL_140x2inS209pos" x="12.6" y="0" z="0" unit="cm"/>
    <position name="SCHL_150x2inS209pos" x="15.119999999999999" y="0" z="0" unit="cm"/>
    <position name="SCHL_16inS209pos" x="17.639999999999997" y="0" z="0" unit="cm"/>
    <position name="SCHL_17inS209pos" x="20.159999999999997" y="0" z="0" unit="cm"/>
    </define>