<solids><polycone name="TGeoPcon0x59" startphi="0" deltaphi="360" aunit="deg" lunit="cm">
      <zplane z="0" rmin="2.9200000762939453" rmax="3.3499999046325684"/>
      <zplane z="0.80000001192092896" rmin="2.9200000762939453" rmax="3.3499999046325684"/>
      <zplane z="0.80000001192092896" rmin="2.9200000762939453" rmax="3"/>
      <zplane z="4.880000114440918" rmin="2.9200000762939453" rmax="3"/>
    </polycone>
    <polycone name="TGeoPcon0x60" startphi="0" deltaphi="360" aunit="deg" lunit="cm">
      <zplane z="0" rmin="3.3599998950958252" rmax="4.3000001907348633"/>
      <zplane z="0.80000001192092896" rmin="3.3599998950958252" rmax="4.3000001907348633"/>
      <zplane z="0.80000001192092896" rmin="3.0299999713897705" rmax="4.3000001907348633"/>
      <zplane z="1.3999999761581421" rmin="3.0299999713897705" rmax="4.3000001907348633"/>
    </polycone>
    <polycone name="TGeoPcon0x61" startphi="0" deltaphi="360" aunit="deg" lunit="cm">
      <zplane z="0" rmin="2.9200000762939453" rmax="3"/>
      <zplane z="3.8199999332427979" rmin="2.9200000762939453" rmax="3"/>
      <zplane z="3.8199999332427979" rmin="2.9200000762939453" rmax="3.5"/>
      <zplane z="4.4099998474121094" rmin="2.9200000762939453" rmax="3.5"/>
      <zplane z="4.4099998474121094" rmin="2.9200000762939453" rmax="3"/>
      <zplane z="5.880000114440918" rmin="2.9200000762939453" rmax="3"/>
    </polycone>
    <polycone name="TGeoPcon0x58" startphi="0" deltaphi="360" aunit="deg" lunit="cm">
      <zplane z="0" rmin="0" rmax="4.3000001907348633"/>
      <zplane z="1.3999999761581421" rmin="0" rmax="4.3000001907348633"/>
      <zplane z="1.3999999761581421" rmin="0" rmax="3"/>
      <zplane z="8.6999998092651367" rmin="0" rmax="3"/>
      <zplane z="8.6999998092651367" rmin="0" rmax="3.5"/>
      <zplane z="9.2899999618530273" rmin="0" rmax="3.5"/>
      <zplane z="9.2899999618530273" rmin="0" rmax="3"/>
      <zplane z="10.760000228881836" rmin="0" rmax="3"/>
    </polycone>
    <polycone name="TGeoPcon0x64" startphi="0" deltaphi="360" aunit="deg" lunit="cm">
      <zplane z="0" rmin="3" rmax="3.5"/>
      <zplane z="207.21000000000001" rmin="3" rmax="3.5"/>
      <zplane z="207.21000000000001" rmin="3.0699999999999998" rmax="3.5699999999999998"/>
      <zplane z="452.30000000000001" rmin="6.1500000000000004" rmax="6.6500000000000004"/>
      <zplane z="459.45001220703125" rmin="6.1500000000000004" rmax="6.6500000000000004"/>
    </polycone>
    <polycone name="TGeoPcon0x63" startphi="0" deltaphi="360" aunit="deg" lunit="cm">
      <zplane z="0" rmin="2.9199999999999999" rmax="3.5"/>
      <zplane z="207.21000000000001" rmin="2.9199999999999999" rmax="3.5"/>
      <zplane z="207.21000000000001" rmin="2.9199999999999999" rmax="3.5699999999999998"/>
      <zplane z="452.30000000000001" rmin="6" rmax="6.6500000000000004"/>
      <zplane z="459.45001220703125" rmin="6" rmax="6.6500000000000004"/>
    </polycone>
    <polycone name="TGeoPcon0x62" startphi="0" deltaphi="360" aunit="deg" lunit="cm">
      <zplane z="0" rmin="0" rmax="3.5"/>
      <zplane z="207.21000000000001" rmin="0" rmax="3.5"/>
      <zplane z="207.21000000000001" rmin="0" rmax="3.5699999999999998"/>
      <zplane z="452.30000000000001" rmin="0" rmax="6.6500000000000004"/>
      <zplane z="459.45001220703125" rmin="0" rmax="6.6500000000000004"/>
    </polycone>
    <intersection name="RB26s2LowerPlie0x1">
      <first ref="RB26s2TorusL"/>
      <second ref="RB26s2TubeL"/>
    </intersection>
    <torus name="RB26s2TorusL" rtor="6.2425923347473145" rmin="0.15759259462356567" rmax="0.18259260058403015" startphi="0" deltaphi="360" aunit="deg" lunit="cm"/>
    <tube name="RB26s2TubeL" rmin="6.059999942779541" rmax="6.2425923347473145" z="0.3651852011680603" startphi="0" deltaphi="360" aunit="deg" lunit="cm"/>
    <tube name="TGeoTube0x45" rmin="6.2425923347473145" rmax="7.0074076652526855" z="0.02500000037252903" startphi="0" deltaphi="360" aunit="deg" lunit="cm"/>
    <intersection name="RB26s2UpperPlie0x1">
      <first ref="RB26s2TorusU"/>
      <second ref="RB26s2TubeU"/>
    </intersection>
    <torus name="RB26s2TorusU" rtor="7.0074076652526855" rmin="0.15759259462356567" rmax="0.18259260058403015" startphi="0" deltaphi="360" aunit="deg" lunit="cm"/>
    <tube name="RB26s2TubeU" rmin="7.0074076652526855" rmax="7.190000057220459" z="0.3651852011680603" startphi="0" deltaphi="360" aunit="deg" lunit="cm"/>
    <tube name="TGeoTube0x44" rmin="6.059999942779541" rmax="7.190000057220459" z="10" startphi="0" deltaphi="360" aunit="deg" lunit="cm"/>
    <tube name="TGeoTube0x46" rmin="6" rmax="6.1500000953674316" z="9" startphi="0" deltaphi="360" aunit="deg" lunit="cm"/>
    <tube name="TGeoTube0x47" rmin="6" rmax="6.1500000953674316" z="11.649999618530273" startphi="0" deltaphi="360" aunit="deg" lunit="cm"/>
    <tube name="TGeoTube0x48" rmin="6.1500000953674316" rmax="9.0500001907348633" z="0.40000000596046448" startphi="0" deltaphi="360" aunit="deg" lunit="cm"/>
    <tube name="TGeoTube0x49" rmin="9.0500001907348633" rmax="9.1000003814697266" z="15" startphi="0" deltaphi="360" aunit="deg" lunit="cm"/>
    <polycone name="TGeoPcon0x65" startphi="0" deltaphi="360" aunit="deg" lunit="cm">
      <zplane z="0" rmin="0" rmax="6.1500000953674316"/>
      <zplane z="6.5" rmin="0" rmax="6.1500000953674316"/>
      <zplane z="6.5" rmin="0" rmax="9.1000003814697266"/>
      <zplane z="21.699999809265137" rmin="0" rmax="9.1000003814697266"/>
      <zplane z="21.699999809265137" rmin="0" rmax="6.1500000953674316"/>
      <zplane z="30.649999618530273" rmin="0" rmax="6.1500000953674316"/>
    </polycone>
    <polycone name="TGeoPcon0x67" startphi="0" deltaphi="360" aunit="deg" lunit="cm">
      <zplane z="0" rmin="6.1500000953674316" rmax="8.5749998092651367"/>
      <zplane z="0.97000002861022949" rmin="6.1500000953674316" rmax="8.5749998092651367"/>
      <zplane z="0.97000002861022949" rmin="6" rmax="8.5749998092651367"/>
      <zplane z="1.2599999904632568" rmin="6" rmax="8.5749998092651367"/>
      <zplane z="1.2599999904632568" rmin="6.1500000953674316" rmax="8.5749998092651367"/>
      <zplane z="2.130000114440918" rmin="6.1500000953674316" rmax="8.5749998092651367"/>
    </polycone>
    <polycone name="TGeoPcon0x66" startphi="0" deltaphi="360" aunit="deg" lunit="cm">
      <zplane z="0" rmin="6.1500000953674316" rmax="8.5749998092651367"/>
      <zplane z="0.97000002861022949" rmin="6.1500000953674316" rmax="8.5749998092651367"/>
      <zplane z="0.97000002861022949" rmin="0" rmax="8.5749998092651367"/>
      <zplane z="1.2599999904632568" rmin="0" rmax="8.5749998092651367"/>
      <zplane z="1.2599999904632568" rmin="0" rmax="8.5749998092651367"/>
      <zplane z="2.130000114440918" rmin="0" rmax="8.5749998092651367"/>
    </polycone>
    </solids>