<solids><polycone name="TGeoPcon0x28" startphi="0" deltaphi="360" aunit="deg" lunit="cm">
      <zplane z="0" rmin="21.5" rmax="26.5"/>
      <zplane z="1.5" rmin="21.5" rmax="26.5"/>
      <zplane z="1.5" rmin="18.399999618530273" rmax="26.5"/>
      <zplane z="3" rmin="18.399999618530273" rmax="26.5"/>
      <zplane z="3" rmin="18.399999618530273" rmax="32.599998474121094"/>
      <zplane z="24" rmin="18.399999618530273" rmax="32.599998474121094"/>
      <zplane z="170.14999389648438" rmin="20.810722351074219" rmax="32.599998474121094"/>
      <zplane z="170.14999389648438" rmin="20.810722351074219" rmax="43.299999237060547"/>
      <zplane z="485" rmin="26.004127502441406" rmax="43.299999237060547"/>
      <zplane z="503.20001220703125" rmin="26" rmax="43.299999237060547"/>
      <zplane z="505.9000244140625" rmin="28.700000762939453" rmax="43.299999237060547"/>
      <zplane z="506.50003051757812" rmin="28.700000762939453" rmax="43.299999237060547"/>
      <zplane z="506.50003051757812" rmin="28.700000762939453" rmax="41.5"/>
      <zplane z="510.50003051757812" rmin="28.700000762939453" rmax="41.5"/>
      <zplane z="510.50003051757812" rmin="28.700000762939453" rmax="30.799999237060547"/>
      <zplane z="512" rmin="28.700000762939453" rmax="30.799999237060547"/>
    </polycone>
    </solids>