<define><position name="SNPB_1inSCHLpos" x="0" y="0" z="-1.24695" unit="cm"/>
    <position name="SKPT_1inSCHLpos" x="0" y="0" z="0" unit="cm"/>
    <position name="SCHL_10x39inS240pos" x="-20.16" y="0" z="0" unit="cm"/>
    <position name="SCHL_20x25inS240pos" x="-10.08" y="0" z="0" unit="cm"/>
    <position name="SCHL_30x22inS240pos" x="0" y="0" z="0" unit="cm"/>
    <position name="SCHL_40x15inS240pos" x="10.08" y="0" z="0" unit="cm"/>
    <position name="SCHL_50x11inS240pos" x="20.16" y="0" z="0" unit="cm"/>
    <position name="S240_1inS040pos" x="0" y="0" z="-0.031" unit="cm"/>
    <position name="S440_1inS040pos" x="0" y="0" z="1.2515000000000001" unit="cm"/>
    </define>