<solids><polycone name="TGeoPcon0x44" startphi="0" deltaphi="360" aunit="deg" lunit="cm">
      <zplane z="0" rmin="0.80000000000000004" rmax="3.5"/>
      <zplane z="1.2699999809265137" rmin="0.80000000000000004" rmax="3.5"/>
      <zplane z="1.2699999809265137" rmin="0.80000000000000004" rmax="1"/>
      <zplane z="4.070000171661377" rmin="0.80000000000000004" rmax="1"/>
      <zplane z="4.070000171661377" rmin="0.80000000000000004" rmax="1.75"/>
      <zplane z="5.6700000762939453" rmin="0.80000000000000004" rmax="1.75"/>
      <zplane z="5.6700000762939453" rmin="0.80000000000000004" rmax="1"/>
      <zplane z="10.869999885559082" rmin="0.80000000000000004" rmax="1"/>
      <zplane z="10.869999885559082" rmin="0.80000000000000004" rmax="2.5"/>
      <zplane z="12.869999885559082" rmin="0.80000000000000004" rmax="2.5"/>
      <zplane z="12.869999885559082" rmin="1.55" rmax="1.75"/>
      <zplane z="18.569999694824219" rmin="0" rmax="1.75"/>
      <zplane z="18.770000457763672" rmin="0" rmax="1.75"/>
      <zplane z="18.770000457763672" rmin="0" rmax="0.75"/>
      <zplane z="19.270000457763672" rmin="0" rmax="0.75"/>
    </polycone>
    </solids>